flask_oidc_auth/__init__.py
flask_oidc_auth/blueprint.py
flask_oidc_auth/extension.py
flask_oidc_auth/spanattrs.py
flask_oidc_auth-0.5.0.dist-info/LICENSE
flask_oidc_auth-0.5.0.dist-info/METADATA
flask_oidc_auth-0.5.0.dist-info/WHEEL
flask_oidc_auth-0.5.0.dist-info/top_level.txt
flask_oidc_auth-0.5.0.dist-info/RECORD
