Metadata-Version: 2.1
Name: flask-oidc-auth
Version: 0.5.0
Summary: Flask extension for an OIDC client.
License: MIT License
Project-URL: Homepage, https://github.com/andycaine/flask-oidc-auth
Project-URL: Documentation, https://github.com/andycaine/flask-oidc-auth?tab=readme-ov-file
Project-URL: Repository, https://github.com/andycaine/flask-oidc-auth.git
Keywords: oidc,authentication,authorization
License-File: LICENSE
Requires-Dist: click
Requires-Dist: flask
Requires-Dist: requests
Requires-Dist: PyJWT
Requires-Dist: cryptography
Requires-Dist: opentelemetry-api
Requires-Dist: opentelemetry-semantic-conventions
